maf_counter/__init__.py
maf_counter/cli.py
maf_counter/bin/maf_counter
maf_counter-0.3.dist-info/LICENSE.md
maf_counter-0.3.dist-info/METADATA
maf_counter-0.3.dist-info/WHEEL
maf_counter-0.3.dist-info/entry_points.txt
maf_counter-0.3.dist-info/top_level.txt
maf_counter-0.3.dist-info/RECORD
