Metadata-Version: 2.1
Name: maf_counter
Version: 0.3
Summary: A high-performance k-mer counting tool for MAF alignments.
Home-page: https://github.com/Georgakopoulos-Soares-lab/MAFcounter
Author: Patsakis Michail , Provatas Kimon, Ilias Georgakopoulos Soares, Ioannis Mouratidis
Author-email: kap6605@psu.edu , mpp5977@psu.edu
Classifier: Programming Language :: Python :: 3
Classifier: License :: OSI Approved :: MIT License
Classifier: Operating System :: POSIX :: Linux
License-File: LICENSE.md
